torch_ms_adapter/__init__.py
torch_ms_adapter/autograd.py
torch_ms_adapter/data.py
torch_ms_adapter/functional.py
torch_ms_adapter/optim.py
torch_ms_adapter/tensor.py
torch_ms_adapter/training.py
torch_ms_adapter/nn/__init__.py
torch_ms_adapter/nn/functional.py
torch_ms_adapter-0.1.4.dist-info/METADATA
torch_ms_adapter-0.1.4.dist-info/WHEEL
torch_ms_adapter-0.1.4.dist-info/top_level.txt
torch_ms_adapter-0.1.4.dist-info/RECORD
