Metadata-Version: 2.1
Name: torch-ms-adapter
Version: 0.1.4
Summary: A PyTorch adapter running on MindSpore
Home-page: https://github.com/your-username/torch-ms-adapter
Author: danny
Author-email: daizelin@icloud.com
Classifier: Programming Language :: Python :: 3
Classifier: License :: OSI Approved :: MIT License
Classifier: Operating System :: OS Independent
Requires-Python: >=3.7
Requires-Dist: mindspore
Requires-Dist: numpy<2.0
